[
  {
    "name": "香椿拌豆腐",
    "reason": "理由：4月正是北京香椿最嫩的时节，香椿芽气味浓烈、健脾开胃，搭配嫩豆腐清爽不腻，多云天气食欲欠佳，凉菜开胃最佳"
  },
  {
    "name": "酱爆鸡丁",
    "reason": "理由：京菜经典做法，酱香浓郁符合北方口味，鸡肉高蛋白低脂，春季补气；多云不晒适合吃些浓味菜品提振食欲"
  },
  {
    "name": "荠菜蛋花汤",
    "reason": "理由：春季荠菜正当鲜，北京近郊田间常见，性凉味甘可清肝明目，蛋花增鲜，12°C左右的凉意中喝一碗热汤暖身又应季"
  },
  {
    "name": "春笋红烧肉",
    "reason": "理由：南方春笋北运已过物流高峰，4月品质仍佳，红烧肉是北方家常硬菜，春笋吸油解腻、鲜嫩回甘，22°C的傍晚适合慢炖一锅"
  },
  {
    "name": "韭菜盒子",
    "reason": "北京春季经典面食，4月韭菜正嫩，多云微凉天气适合吃温热的煎烙面食，暖胃又应季"
  },
  {
    "name": "榆钱蒸饭",
    "reason": "北京传统春令野菜，4月榆钱最鲜嫩，蒸制保留原味，清淡适应当日12~22°C舒适气温"
  },
  {
    "name": "葱烧海参",
    "reason": "北京鲁菜代表，春季海参肥厚，葱烧做法浓香厚重，适合北京偏北方口味的加餐补益"
  },
  {
    "name": "凉拌马齿苋",
    "reason": "春季时令野菜，北京郊区常见，微酸爽口清火，多云天气不燥正好消食"
  },
  {
    "name": "白灼芦笋",
    "reason": "4月芦笋当季鲜嫩，北京讲究清淡养生，白灼做法最大限度保留春蔬清甜，适合当前温和天气"
  },
  {
    "name": "酱牛肉",
    "reason": "北京家常硬菜，春季进补佳品，酱香浓郁耐存放，佐酒下饭皆宜，契合北方饮食习惯"
  },
  {
    "name": "豌豆黄",
    "reason": "北京传统春季甜品，4月新豌豆上市，清凉微甜，多云天气食用不腻，饭后消食上品"
  },
  {
    "name": "醋溜木须",
    "reason": "北京家常菜经典，春季鸡蛋新鲜、木耳爽脆，酸甜开胃，适合多云天气食欲平稳时的下饭菜"
  },
  {
    "name": "香椿炒鸡蛋",
    "reason": "4月香椿正嫩，北京家常经典，多云微凉天气适合热炒补阳气，与香椿拌豆腐不重复，一拌一炒风味各异"
  },
  {
    "name": "蒜泥莴笋丝",
    "reason": "春季莴笋刚上市，北京凉拌菜解春燥，12~22度阴天适合清爽凉菜开胃"
  },
  {
    "name": "酱焖鲤鱼",
    "reason": "北京春季讲究\"春鲜入水\"，酱焖是京帮浓口特色，多云天气适合浓郁炖菜暖身"
  },
  {
    "name": "炸槐花丸子",
    "reason": "北京四月底槐花飘香，时令限定的京味小吃，酥脆口感适合春游佐餐"
  },
  {
    "name": "菠菜粉丝汆丸子",
    "reason": "春季菠菜鲜嫩补血，北京家常汆汤做法温润不腻，适合多云温差大的天气暖胃"
  },
  {
    "name": "花椒芽拌腐竹",
    "reason": "花椒芽是京郊春季山野菜，搭配腐竹是典型京式凉菜，麻香开胃解春困"
  },
  {
    "name": "菜心炒河虾",
    "reason": "春虾头籽肥美，北京馆子春季常备，清炒保留鲜甜，22度上限天气适合清淡小炒"
  },
  {
    "name": "小米绿豆粥",
    "reason": "北京春季养肝传统，绿豆清火小米养胃，多云天早晚微凉宜喝热粥润燥"
  },
  {
    "name": "油焖春笋尖",
    "reason": "春季北京菜馆必推，本地虽非产笋区但冷链春笋正当季，多云凉爽天气适合浓油赤酱焖制，开胃驱春乏"
  },
  {
    "name": "蒜苗回锅肉",
    "reason": "北京春季蒜苗最嫩，搭配川味回锅做法适合北方人重口味，12~22°C微凉天气吃温热火候菜正合适"
  },
  {
    "name": "艾窝窝",
    "reason": "北京传统春日节令小吃，糯米艾草清香祛湿，春季清明前后应景，凉拌冷食适合多云不燥的天气"
  },
  {
    "name": "清炒黄花菜",
    "reason": "4月鲜黄花菜上市，北京讲究\"春吃芽\"，清淡快炒保留脆嫩，多云日无烈日正宜清爽饮食"
  },
  {
    "name": "糊塌子",
    "reason": "老北京春季家常面食，西葫芦应季鲜嫩，擦丝加面糊煎制，外酥里软，适合早晚偏凉的春日佐小米粥"
  },
  {
    "name": "醋椒野蘑菇",
    "reason": "京郊春季山菇上市，酸辣汤底开胃驱湿，多云天气微凉喝一碗暖身不上火，契合北方酸辣口传统"
  },
  {
    "name": "槐花鸡蛋饼",
    "reason": "4月底北京槐花开，时令限定不可错过，蛋饼做法保留花香，春季食花养生，老少咸宜"
  },
  {
    "name": "酱香拌苜蓿芽",
    "reason": "北京人称\"草头\"，春季苜蓿芽最嫩，简单酱拌低脂爽口，适合春困湿气重时清肠提神"
  },
  {
    "name": "泥鳅钻豆腐",
    "reason": "合肥地处江淮，春季泥鳅正值肥嫩，小雨阴冷天气食用温补驱寒，泥鳅与豆腐同炖营养丰富，是本地经典土菜"
  },
  {
    "name": "清蒸鲻鱼",
    "reason": "4月鲻鱼洄游至巢湖最为鲜美，合肥人喜清蒸保留本味，小雨天吃清蒸鱼温润不腻，适合春季滋补"
  },
  {
    "name": "莴笋叶炒咸肉",
    "reason": "合肥春季多腌咸肉，莴笋叶此时最嫩，搭配咸肉爆炒咸鲜下饭，充分利用时蔬边角料，符合本地节俭食俗"
  },
  {
    "name": "鸭血粉丝煮春笋",
    "reason": "合肥鸭血粉丝为街头名吃，加入当季春笋提鲜增脆，热汤驱散雨后寒意，口感层次丰富"
  },
  {
    "name": "蒿子粑粑",
    "reason": "清明前后江淮一带必食蒿子粑，用艾蒿与糯米粉煎制，应季祛湿散寒，小雨天气温偏低更需此类暖身小吃"
  },
  {
    "name": "茄汁蚕豆",
    "reason": "合肥4月蚕豆刚上市极嫩，茄汁微酸开胃去春湿，酸甜口感适合阴雨天提振食欲"
  },
  {
    "name": "泥鳅挂面",
    "reason": "合肥长丰一带春季家常做法，泥鳅煮汤下面，汤浓面滑，雨天食用暖胃驱寒，时令与地域特色兼备"
  },
  {
    "name": "凉拌蕨菜",
    "reason": "春季蕨菜从江淮丘陵地带冒出，焯水凉拌酸辣爽口，去湿清火，合肥农家乐春季必上凉菜"
  },
  {
    "name": "清炒蚕豆米",
    "reason": "合肥春季蚕豆正当季，嫩蚕豆米清甜软糯，清炒最能保留春鲜，本地家常快手菜"
  },
  {
    "name": "香椿头炖蛋",
    "reason": "香椿谷雨前最嫩，合肥人嗜香椿，炖蛋比炒蛋更滑嫩养胃，适合乍暖还寒的春夜"
  },
  {
    "name": "毛豆米烧土鸡",
    "reason": "皖中丘陵散养土鸡肉质紧实，毛豆米四月荚饱粒圆，酱烧咸鲜下饭，是合肥土菜馆招牌"
  },
  {
    "name": "枸杞头炒竹笋",
    "reason": "枸杞嫩芽为江淮春蔬上品，搭配春笋清炒，微苦回甘，清热明目，顺应春季养肝"
  },
  {
    "name": "腌笃鲜",
    "reason": "合肥虽非江南核心但饮食交融，春笋配咸五花肉、鲜肉慢炖，汤汁醇厚，春季祛湿补虚"
  },
  {
    "name": "芦蒿炒香干",
    "reason": "芜湖至合肥一带春季必吃芦蒿，配白干快炒，脆嫩清香，有\"蒌蒿满地芦芽短\"的诗意时令感"
  },
  {
    "name": "槐花炒腊肉",
    "reason": "皖西山区四月槐花盛开，腊味与花香碰撞，咸香鲜甜，是合肥周边农家乐春季限定"
  },
  {
    "name": "蒲公英炒肉丝",
    "reason": "春季合肥郊外蒲公英正嫩，阴冷天气温炒补暖，肉丝增香驱寒，兼具清火去湿之效"
  },
  {
    "name": "刀鱼馄饨",
    "reason": "4月长江刀鱼最肥美，合肥近巢湖水系素有尝刀鱼习俗，包馄饨温润驱春寒"
  },
  {
    "name": "蚕豆焖饭",
    "reason": "合肥本地蚕豆4月上市，焖饭做法契合江淮家常口味，阴天食用暖胃饱腹"
  },
  {
    "name": "腌鲜鳜鱼",
    "reason": "徽州腌鲜技法在合肥广泛流传，四月鳜鱼渐肥，阴湿天气发酵风味更显醇厚"
  },
  {
    "name": "秧草烧河蚌",
    "reason": "苏皖交界春季河蚌最佳，秧草即南苜蓿嫩尖，合肥沿巢湖一带时令标配，祛湿养肝"
  },
  {
    "name": "桃花鳜鱼砂锅",
    "reason": "4月合肥桃花汛鳜鱼鲜肥，砂锅炖煮适合19°C以下阴冷天气，汤醇暖身"
  },
  {
    "name": "艾草粑粑配米糊",
    "reason": "合肥清明后艾草尚嫩，制成咸口粑粑配小米糊，阴天食用温润健脾应季养生"
  },
  {
    "name": "清蒸巢湖银鱼",
    "reason": "推荐理由：春季巢湖银鱼最肥美，合肥地处巢湖之滨，晴日气温适宜清淡鲜食，清蒸最能保留银鱼嫩滑鲜甜，本地家常首选"
  },
  {
    "name": "马兰头拌五香干",
    "reason": "推荐理由：清明前后马兰头最嫩，合肥人春季爱食野菜，凉拌开胃驱春困，五香干增香提味，冷热交替天气宜清爽"
  },
  {
    "name": "蚕豆焖仔鸡",
    "reason": "推荐理由：4月鲜蚕豆颗粒饱满粉糯，搭配春季小仔鸡肉质细嫩，红烧焖制浓香下饭，合肥乡土菜经典时令搭配"
  },
  {
    "name": "盐水河虾蘸醋姜",
    "reason": "推荐理由：春季河虾带籽正当时，合肥沿淮近湖河鲜丰富，盐水白灼轻烹锁鲜，晴暖天气佐姜醋去寒湿"
  },
  {
    "name": "油渣炒香椿芽",
    "reason": "推荐理由：香椿赏味期短仅剩半月，搭配肥膘油渣爆炒提香，合肥老派做法浓油赤酱补春寒，10°C早晚温差需暖食"
  },
  {
    "name": "荠菜鲜肉大馄饨",
    "reason": "推荐理由：与已有蛋花汤不同，改为包馅饱腹，四月末荠菜渐老做馅最香，合肥早点习惯，晴日适合带汤热食暖身"
  },
  {
    "name": "青团",
    "reason": "推荐理由：合肥周边皖南青团正上市，艾草汁和糯米粉手工现蒸，晴好天气适合踏青携带，甜咸皆可，春食青团为江淮民俗"
  },
  {
    "name": "红烧泥鳅烧豆腐",
    "reason": "推荐理由：与\"泥鳅钻豆腐\"做法不同，此为红烧浓汁，春季泥鳅肥美带卵，合肥肥东肥西家常做法，配鲜豆腐滋补暖中，应对乍暖还寒"
  },
  {
    "name": "清炒荷叶嫩尖",
    "reason": "5月合肥城郊池塘荷叶初展，嫩尖微苦回甘，晴日微凉适合清淡去火，搭配本地土猪油清炒，极具时令特色"
  },
  {
    "name": "虾籽茭白",
    "reason": "初夏茭白正肥，巢湖流域盛产，加入虾籽提鲜，合肥沿江风味经典时蔬，温润不燥适合当前气温"
  },
  {
    "name": "泥鳅炖丝瓜",
    "reason": "5月泥鳅最肥美已过产卵期，丝瓜正当嫩口，合肥土菜重鲜滑，晴凉天气喝一碗暖而不腻"
  },
  {
    "name": "槐花酿豆腐",
    "reason": "5月初合肥槐花尾声，将槐花拌肉末酿入水豆腐蒸制，比炸丸子更显清淡，契合11~21℃凉爽天气"
  },
  {
    "name": "盐水螺蛳配紫苏",
    "reason": "合肥大圩、三十岗一带春末螺蛳肥嫩无籽，紫苏去腥提香，佐酒下饭均宜，是本地夜市时令招牌"
  },
  {
    "name": "香椿拌松花蛋",
    "reason": "已有香椿系菜品但未入蛋品类，松花蛋为合肥老牌下酒菜，晴凉天佐粥佐酒皆宜，鲜香开胃"
  },
  {
    "name": "莴笋筒骨汤",
    "reason": "莴笋正当季且已有凉拌做法但未入汤品，筒骨浓汤打底，清炖不腻，适合当前昼夜温差大需温补"
  },
  {
    "name": "蚕豆酱爆毛肚",
    "reason": "春末蚕豆新嫩、毛肚脆爽，合肥酱爆技法浓郁下饭，晴日微凉时温中暖胃，本地土菜创新搭配"
  }
]